chronotrack/__init__.py
chronotrack/cli.py
chronotrack/email_sender.py
chronotrack/generate_report.py
chronotrack/report_data.py
chronotrack/tracker.py
chronotrack/utils.py
chronotrack_cli-0.1.9.dist-info/licenses/LICENSE
chronotrack_cli-0.1.9.dist-info/METADATA
chronotrack_cli-0.1.9.dist-info/WHEEL
chronotrack_cli-0.1.9.dist-info/entry_points.txt
chronotrack_cli-0.1.9.dist-info/top_level.txt
chronotrack_cli-0.1.9.dist-info/RECORD
