Metadata-Version: 2.4
Name: chronotrack-cli
Version: 0.1.9
Summary: A developer-focused CLI time tracker with tagging, breaks, and rich analytics.
Author-email: Shahriyar Ahmed Mahir <nafismahir@icloud.com>
License: MIT
Project-URL: Homepage, https://github.com/mahirvisoredbroom855/ChronoTrack
Project-URL: Repository, https://github.com/mahirvisoredbroom855/ChronoTrack
Project-URL: Issues, https://github.com/mahirvisoredbroom855/ChronoTrack/issues
Keywords: cli,productivity,time-tracking,terminal,typer
Classifier: Programming Language :: Python :: 3
Classifier: License :: OSI Approved :: MIT License
Classifier: Operating System :: OS Independent
Requires-Python: >=3.8
License-File: LICENSE
Dynamic: license-file
